designs/UART/src/uart_tx.v
//////////////////////////////////////////////////////////////////////////////////
//                                                                              //
//                                                                              //
//  Author: meisq                                                               //
//          msq@qq.com                                                          //
//          ALINX(shanghai) Technology Co.,Ltd                                  //
//          heijin                                                              //
//     WEB: http://www.alinx.cn/                                                //
//     BBS: http://www.heijin.org/                                              //
//                                                                              //
//////////////////////////////////////////////////////////////////////////////////
//                                                                              //
// Copyright (c) 2017,ALINX(shanghai) Technology Co.,Ltd                        //
//                    All rights reserved                                       //
//                                                                              //
// This source file may be used and distributed without restriction provided    //
// that this copyright statement is not removed from the file and that any      //
// derivative work contains the original copyright notice and the associated    //
// disclaimer.                                                                  //
//                                                                              //
//////////////////////////////////////////////////////////////////////////////////

//================================================================================
//  Revision History:
//  Date          By            Revision    Change Description
//--------------------------------------------------------------------------------
//2017/8/1                    1.0          Original
//*******************************************************************************/
module uart_tx
#(
	parameter CLK_FRE = 50,      //clock frequency(Mhz)
	parameter BAUD_RATE = 115200 //serial baud rate
)
(
	input                        clk,              //clock input
	input                        rst_n,            //asynchronous reset input, low active 
	input[7:0]                   tx_data,          //data to send
	input                        tx_data_valid,    //data to be sent is valid
	output reg                   tx_data_ready,    //send ready
	output                       tx_pin            //serial data output
);
//calculates the clock cycle for baud rate 
localparam                       CYCLE = CLK_FRE * 1000000 / BAUD_RATE;
//state machine code
localparam                       S_IDLE       = 1;
localparam                       S_START      = 2;//start bit
localparam                       S_SEND_BYTE  = 3;//data bits
localparam                       S_STOP       = 4;//stop bit
reg[2:0]                         state;
reg[2:0]                         next_state;
reg[15:0]                        cycle_cnt; //baud counter
reg[2:0]                         bit_cnt;//bit counter
reg[7:0]                         tx_data_latch; //latch data to send
reg                              tx_reg; //serial data output
assign tx_pin = tx_reg;
always@(posedge clk or negedge rst_n)
begin
	if(rst_n == 1'b0)
		state <= S_IDLE;
	else
		state <= next_state;
end

always@(*)
begin
	case(state)
		S_IDLE:
			if(tx_data_valid == 1'b1)
				next_state <= S_START;
			else
				next_state <= S_IDLE;
		S_START:
			if(cycle_cnt == CYCLE - 1)
				next_state <= S_SEND_BYTE;
			else
				next_state <= S_START;
		S_SEND_BYTE:
			if(cycle_cnt == CYCLE - 1  && bit_cnt == 3'd7)
				next_state <= S_STOP;
			else
				next_state <= S_SEND_BYTE;
		S_STOP:
			if(cycle_cnt == CYCLE - 1)
				next_state <= S_IDLE;
			else
				next_state <= S_STOP;
		default:
			next_state <= S_IDLE;
	endcase
end
always@(posedge clk or negedge rst_n)
begin
	if(rst_n == 1'b0)
		begin
			tx_data_ready <= 1'b1;
		end
	else if(state == S_IDLE)
		if(tx_data_valid == 1'b1)
			tx_data_ready <= 1'b0;
		else
			tx_data_ready <= tx_data_ready;
	else if(state == S_STOP && cycle_cnt == CYCLE - 1)
			tx_data_ready <= 1'b1;
end


always@(posedge clk or negedge rst_n)
begin
	if(rst_n == 1'b0)
		begin
			tx_data_latch <= 8'd0;
		end
	else if(state == S_IDLE && tx_data_valid == 1'b1)
			tx_data_latch <= tx_data;
		
end

always@(posedge clk or negedge rst_n)
begin
	if(rst_n == 1'b0)
		begin
			bit_cnt <= 3'd0;
		end
	else if(state == S_SEND_BYTE)
		if(cycle_cnt == CYCLE - 1)
			bit_cnt <= bit_cnt + 3'd1;
		else
			bit_cnt <= bit_cnt;
	else
		bit_cnt <= 3'd0;
end


always@(posedge clk or negedge rst_n)
begin
	if(rst_n == 1'b0)
		cycle_cnt <= 16'd0;
	else if((state == S_SEND_BYTE && cycle_cnt == CYCLE - 1) || next_state != state)
		cycle_cnt <= 16'd0;
	else
		cycle_cnt <= cycle_cnt + 16'd1;	
end

always@(posedge clk or negedge rst_n)
begin
	if(rst_n == 1'b0)
		tx_reg <= 1'b1;
	else
		case(state)
			S_IDLE,S_STOP:
				tx_reg <= 1'b1; 
			S_START:
				tx_reg <= 1'b0; 
			S_SEND_BYTE:
				tx_reg <= tx_data_latch[bit_cnt];
			default:
				tx_reg <= 1'b1; 
		endcase
end

endmodule

designs/UART/src/uart_rx.v
//////////////////////////////////////////////////////////////////////////////////
//                                                                              //
//                                                                              //
//  Author: meisq                                                               //
//          msq@qq.com                                                          //
//          ALINX(shanghai) Technology Co.,Ltd                                  //
//          heijin                                                              //
//     WEB: http://www.alinx.cn/                                                //
//     BBS: http://www.heijin.org/                                              //
//                                                                              //
//////////////////////////////////////////////////////////////////////////////////
//                                                                              //
// Copyright (c) 2017,ALINX(shanghai) Technology Co.,Ltd                        //
//                    All rights reserved                                       //
//                                                                              //
// This source file may be used and distributed without restriction provided    //
// that this copyright statement is not removed from the file and that any      //
// derivative work contains the original copyright notice and the associated    //
// disclaimer.                                                                  //
//                                                                              //
//////////////////////////////////////////////////////////////////////////////////

//================================================================================
//  Revision History:
//  Date          By            Revision    Change Description
//--------------------------------------------------------------------------------
//2017/8/1                    1.0          Original
//*******************************************************************************/
module uart_rx
#(
	parameter CLK_FRE = 50,      //clock frequency(Mhz)
	parameter BAUD_RATE = 115200 //serial baud rate
)
(
	input                        clk,              //clock input
	input                        rst_n,            //asynchronous reset input, low active 
	output reg[7:0]              rx_data,          //received serial data
	output reg                   rx_data_valid,    //received serial data is valid
	input                        rx_data_ready,    //data receiver module ready
	input                        rx_pin            //serial data input
);
//calculates the clock cycle for baud rate 
localparam                       CYCLE = CLK_FRE * 1000000 / BAUD_RATE;
//state machine code
localparam                       S_IDLE      = 1;
localparam                       S_START     = 2; //start bit
localparam                       S_REC_BYTE  = 3; //data bits
localparam                       S_STOP      = 4; //stop bit
localparam                       S_DATA      = 5;

reg[2:0]                         state;
reg[2:0]                         next_state;
reg                              rx_d0;            //delay 1 clock for rx_pin
reg                              rx_d1;            //delay 1 clock for rx_d0
wire                             rx_negedge;       //negedge of rx_pin
reg[7:0]                         rx_bits;          //temporary storage of received data
reg[15:0]                        cycle_cnt;        //baud counter
reg[2:0]                         bit_cnt;          //bit counter

assign rx_negedge = rx_d1 && ~rx_d0;

always@(posedge clk or negedge rst_n)
begin
	if(rst_n == 1'b0)
	begin
		rx_d0 <= 1'b0;
		rx_d1 <= 1'b0;	
	end
	else
	begin
		rx_d0 <= rx_pin;
		rx_d1 <= rx_d0;
	end
end


always@(posedge clk or negedge rst_n)
begin
	if(rst_n == 1'b0)
		state <= S_DATA;
	else
		state <= next_state;
end

always@(*)
begin
	case(state)
		S_IDLE:
			if(rx_negedge)
				next_state <= S_START;
			else
				next_state <= S_IDLE;
		S_START:
			if(cycle_cnt == CYCLE - 1)//one data cycle 
				next_state <= S_REC_BYTE;
			else
				next_state <= S_START;
		S_REC_BYTE:
			if(cycle_cnt == CYCLE - 1  && bit_cnt == 3'd7)  //receive 8bit data
				next_state <= S_STOP;
			else
				next_state <= S_REC_BYTE;
		S_STOP:
			if(cycle_cnt == CYCLE/2 - 1)//half bit cycle,to avoid missing the next byte receiver
				next_state <= S_DATA;
			else
				next_state <= S_STOP;
		S_DATA:
			if(rx_data_ready)    //data receive complete
				next_state <= S_IDLE;
			else
				next_state <= S_DATA;
		default:
			next_state <= S_IDLE;
	endcase
end

always@(posedge clk or negedge rst_n)
begin
	if(rst_n == 1'b0)
		rx_data_valid <= 1'b0;
	else if(state == S_STOP && next_state != state)
		rx_data_valid <= 1'b1;
	else if(state == S_DATA && rx_data_ready)
		rx_data_valid <= 1'b0;
end

always@(posedge clk or negedge rst_n)
begin
	if(rst_n == 1'b0)
		rx_data <= 8'd0;
	else if(state == S_STOP && next_state != state)
		rx_data <= rx_bits;//latch received data
end

always@(posedge clk or negedge rst_n)
begin
	if(rst_n == 1'b0)
		begin
			bit_cnt <= 3'd0;
		end
	else if(state == S_REC_BYTE)
		if(cycle_cnt == CYCLE - 1)
			bit_cnt <= bit_cnt + 3'd1;
		else
			bit_cnt <= bit_cnt;
	else
		bit_cnt <= 3'd0;
end


always@(posedge clk or negedge rst_n)
begin
	if(rst_n == 1'b0)
		cycle_cnt <= 16'd0;
	else if((state == S_REC_BYTE && cycle_cnt == CYCLE - 1) || next_state != state)
		cycle_cnt <= 16'd0;
	else
		cycle_cnt <= cycle_cnt + 16'd1;	
end
//receive serial data bit data
always@(posedge clk or negedge rst_n)
begin
	if(rst_n == 1'b0)
		rx_bits <= 8'd0;
	else if(state == S_REC_BYTE && cycle_cnt == CYCLE/2 - 1)
		rx_bits[bit_cnt] <= rx_pin;
	else
		rx_bits <= rx_bits; 
end
endmodule

designs/UART/tb/uart_tb.v
`timescale 1ns/1ps  // Add timescale directive for simulation compatibility

module uart_tb();

    reg                                 clk                         ;
    reg                                 rst_n                       ;

    initial begin
        clk = 1'b0;
        rst_n = 1'b0;
        #50;
        rst_n = 1'b1;
    end

    always #5 clk = ~clk;                                           //100M

    // output declaration of module uart_rx
    wire                                rx_pin                      ;
    wire               [   7: 0]        rx_data                     ;
    wire                                rx_data_valid               ;

    reg                                 rx_data_ready               ;

    uart_rx #(
    .CLK_FRE                            (100                       ),
    .BAUD_RATE                          (115200)                   ) 
    u_uart_rx(
    .clk                                (clk                       ),
    .rst_n                              (rst_n                     ),
    .rx_data                            (rx_data                   ),
    .rx_data_valid                      (rx_data_valid             ),
    .rx_data_ready                      (rx_data_ready             ),
    .rx_pin                             (rx_pin                    ) 
    );
    
    
    // output declaration of module uart_tx
    wire                                tx_pin                      ;
    wire                                tx_data_ready               ;

    reg                [   7: 0]        tx_data                     ;
    reg                                 tx_data_valid               ;

    uart_tx #(
    .CLK_FRE                            (100                       ),
    .BAUD_RATE                          (115200)                   ) 
    u_uart_tx(
    .clk                                (clk                       ),
    .rst_n                              (rst_n                     ),
    .tx_data                            (tx_data                   ),
    .tx_data_valid                      (tx_data_valid             ),
    .tx_data_ready                      (tx_data_ready             ),
    .tx_pin                             (tx_pin                    ) 
    );

    initial begin
        tx_data = 8'hA5;
        tx_data_valid = 1'b0;
        rx_data_ready = 1'b1;

        #100;
        tx_data_valid = 1'b1;

        #10;
        tx_data_valid = 1'b0;

        wait(rx_data_valid);
        rx_data_ready = 1'b0;

        wait(tx_data_ready == 1'b1);
        #10;
        tx_data = 8'h3C;
        tx_data_valid = 1'b1;


        #10;
        tx_data_valid = 1'b0;

    end

    assign                              rx_pin                      = tx_pin               ;

    initial begin
        $dumpfile("icarus/uart_tb.vcd"); // Use relative path, avoid leading slash on Windows
        $dumpvars(0, uart_tb);
        #200000;
        $finish();
    end

endmodule

designs/UART/icarus/uart_tb.vcd
$date
	Thu Nov 27 21:50:56 2025
$end
$version
	Icarus Verilog
$end
$timescale
	1ps
$end
$scope module uart_tb $end
$var wire 1 ! rx_pin $end
$var wire 1 " tx_pin $end
$var wire 1 # tx_data_ready $end
$var wire 1 $ rx_data_valid $end
$var wire 8 % rx_data [7:0] $end
$var reg 1 & clk $end
$var reg 1 ' rst_n $end
$var reg 1 ( rx_data_ready $end
$var reg 8 ) tx_data [7:0] $end
$var reg 1 * tx_data_valid $end
$scope module u_uart_rx $end
$var wire 1 & clk $end
$var wire 1 ' rst_n $end
$var wire 1 ( rx_data_ready $end
$var wire 1 + rx_negedge $end
$var wire 1 ! rx_pin $end
$var parameter 32 , BAUD_RATE $end
$var parameter 32 - CLK_FRE $end
$var parameter 64 . CYCLE $end
$var parameter 32 / S_DATA $end
$var parameter 32 0 S_IDLE $end
$var parameter 32 1 S_REC_BYTE $end
$var parameter 32 2 S_START $end
$var parameter 32 3 S_STOP $end
$var reg 3 4 bit_cnt [2:0] $end
$var reg 16 5 cycle_cnt [15:0] $end
$var reg 3 6 next_state [2:0] $end
$var reg 8 7 rx_bits [7:0] $end
$var reg 1 8 rx_d0 $end
$var reg 1 9 rx_d1 $end
$var reg 8 : rx_data [7:0] $end
$var reg 1 $ rx_data_valid $end
$var reg 3 ; state [2:0] $end
$upscope $end
$scope module u_uart_tx $end
$var wire 1 & clk $end
$var wire 1 ' rst_n $end
$var wire 8 < tx_data [7:0] $end
$var wire 1 * tx_data_valid $end
$var wire 1 " tx_pin $end
$var parameter 32 = BAUD_RATE $end
$var parameter 32 > CLK_FRE $end
$var parameter 64 ? CYCLE $end
$var parameter 32 @ S_IDLE $end
$var parameter 32 A S_SEND_BYTE $end
$var parameter 32 B S_START $end
$var parameter 32 C S_STOP $end
$var reg 3 D bit_cnt [2:0] $end
$var reg 16 E cycle_cnt [15:0] $end
$var reg 3 F next_state [2:0] $end
$var reg 3 G state [2:0] $end
$var reg 8 H tx_data_latch [7:0] $end
$var reg 1 # tx_data_ready $end
$var reg 1 " tx_reg $end
$upscope $end
$upscope $end
$enddefinitions $end
$comment Show the parameter values. $end
$dumpall
b100 C
b10 B
b11 A
b1 @
b1101100100 ?
b1100100 >
b11100001000000000 =
b100 3
b10 2
b11 1
b1 0
b101 /
b1101100100 .
b1100100 -
b11100001000000000 ,
$end
#0
$dumpvars
b0 H
b1 G
b1 F
b0 E
b0 D
b10100101 <
b101 ;
b0 :
09
08
b0 7
b1 6
b0 5
b0 4
0+
0*
b10100101 )
1(
0'
0&
b0 %
0$
1#
1"
1!
$end
#5000
1&
#10000
0&
#15000
1&
#20000
0&
#25000
1&
#30000
0&
#35000
1&
#40000
0&
#45000
1&
#50000
0&
1'
#55000
18
b1 ;
b1 E
1&
#60000
0&
#65000
b10 E
b1 5
19
1&
#70000
0&
#75000
b10 5
b11 E
1&
#80000
0&
#85000
b100 E
b11 5
1&
#90000
0&
#95000
b100 5
b101 E
1&
#100000
b10 F
0&
1*
#105000
b0 E
b10100101 H
0#
b10 G
b101 5
1&
#110000
0&
0*
#115000
b110 5
b1 E
0!
0"
1&
#120000
0&
#125000
b10 6
1+
b10 E
b111 5
08
1&
#130000
0&
#135000
0+
09
b10 ;
b0 5
b11 E
1&
#140000
0&
#145000
b100 E
b1 5
1&
#150000
0&
#155000
b10 5
b101 E
1&
#160000
0&
#165000
b110 E
b11 5
1&
#170000
0&
#175000
b100 5
b111 E
1&
#180000
0&
#185000
b1000 E
b101 5
1&
#190000
0&
#195000
b110 5
b1001 E
1&
#200000
0&
#205000
b1010 E
b111 5
1&
#210000
0&
#215000
b1000 5
b1011 E
1&
#220000
0&
#225000
b1100 E
b1001 5
1&
#230000
0&
#235000
b1010 5
b1101 E
1&
#240000
0&
#245000
b1110 E
b1011 5
1&
#250000
0&
#255000
b1100 5
b1111 E
1&
#260000
0&
#265000
b10000 E
b1101 5
1&
#270000
0&
#275000
b1110 5
b10001 E
1&
#280000
0&
#285000
b10010 E
b1111 5
1&
#290000
0&
#295000
b10000 5
b10011 E
1&
#300000
0&
#305000
b10100 E
b10001 5
1&
#310000
0&
#315000
b10010 5
b10101 E
1&
#320000
0&
#325000
b10110 E
b10011 5
1&
#330000
0&
#335000
b10100 5
b10111 E
1&
#340000
0&
#345000
b11000 E
b10101 5
1&
#350000
0&
#355000
b10110 5
b11001 E
1&
#360000
0&
#365000
b11010 E
b10111 5
1&
#370000
0&
#375000
b11000 5
b11011 E
1&
#380000
0&
#385000
b11100 E
b11001 5
1&
#390000
0&
#395000
b11010 5
b11101 E
1&
#400000
0&
#405000
b11110 E
b11011 5
1&
#410000
0&
#415000
b11100 5
b11111 E
1&
#420000
0&
#425000
b100000 E
b11101 5
1&
#430000
0&
#435000
b11110 5
b100001 E
1&
#440000
0&
#445000
b100010 E
b11111 5
1&
#450000
0&
#455000
b100000 5
b100011 E
1&
#460000
0&
#465000
b100100 E
b100001 5
1&
#470000
0&
#475000
b100010 5
b100101 E
1&
#480000
0&
#485000
b100110 E
b100011 5
1&
#490000
0&
#495000
b100100 5
b100111 E
1&
#500000
0&
#505000
b101000 E
b100101 5
1&
#510000
0&
#515000
b100110 5
b101001 E
1&
#520000
0&
#525000
b101010 E
b100111 5
1&
#530000
0&
#535000
b101000 5
b101011 E
1&
#540000
0&
#545000
b101100 E
b101001 5
1&
#550000
0&
#555000
b101010 5
b101101 E
1&
#560000
0&
#565000
b101110 E
b101011 5
1&
#570000
0&
#575000
b101100 5
b101111 E
1&
#580000
0&
#585000
b110000 E
b101101 5
1&
#590000
0&
#595000
b101110 5
b110001 E
1&
#600000
0&
#605000
b110010 E
b101111 5
1&
#610000
0&
#615000
b110000 5
b110011 E
1&
#620000
0&
#625000
b110100 E
b110001 5
1&
#630000
0&
#635000
b110010 5
b110101 E
1&
#640000
0&
#645000
b110110 E
b110011 5
1&
#650000
0&
#655000
b110100 5
b110111 E
1&
#660000
0&
#665000
b111000 E
b110101 5
1&
#670000
0&
#675000
b110110 5
b111001 E
1&
#680000
0&
#685000
b111010 E
b110111 5
1&
#690000
0&
#695000
b111000 5
b111011 E
1&
#700000
0&
#705000
b111100 E
b111001 5
1&
#710000
0&
#715000
b111010 5
b111101 E
1&
#720000
0&
#725000
b111110 E
b111011 5
1&
#730000
0&
#735000
b111100 5
b111111 E
1&
#740000
0&
#745000
b1000000 E
b111101 5
1&
#750000
0&
#755000
b111110 5
b1000001 E
1&
#760000
0&
#765000
b1000010 E
b111111 5
1&
#770000
0&
#775000
b1000000 5
b1000011 E
1&
#780000
0&
#785000
b1000100 E
b1000001 5
1&
#790000
0&
#795000
b1000010 5
b1000101 E
1&
#800000
0&
#805000
b1000110 E
b1000011 5
1&
#810000
0&
#815000
b1000100 5
b1000111 E
1&
#820000
0&
#825000
b1001000 E
b1000101 5
1&
#830000
0&
#835000
b1000110 5
b1001001 E
1&
#840000
0&
#845000
b1001010 E
b1000111 5
1&
#850000
0&
#855000
b1001000 5
b1001011 E
1&
#860000
0&
#865000
b1001100 E
b1001001 5
1&
#870000
0&
#875000
b1001010 5
b1001101 E
1&
#880000
0&
#885000
b1001110 E
b1001011 5
1&
#890000
0&
#895000
b1001100 5
b1001111 E
1&
#900000
0&
#905000
b1010000 E
b1001101 5
1&
#910000
0&
#915000
b1001110 5
b1010001 E
1&
#920000
0&
#925000
b1010010 E
b1001111 5
1&
#930000
0&
#935000
b1010000 5
b1010011 E
1&
#940000
0&
#945000
b1010100 E
b1010001 5
1&
#950000
0&
#955000
b1010010 5
b1010101 E
1&
#960000
0&
#965000
b1010110 E
b1010011 5
1&
#970000
0&
#975000
b1010100 5
b1010111 E
1&
#980000
0&
#985000
b1011000 E
b1010101 5
1&
#990000
0&
#995000
b1010110 5
b1011001 E
1&
#1000000
0&
#1005000
b1011010 E
b1010111 5
1&
#1010000
0&
#1015000
b1011000 5
b1011011 E
1&
#1020000
0&
#1025000
b1011100 E
b1011001 5
1&
#1030000
0&
#1035000
b1011010 5
b1011101 E
1&
#1040000
0&
#1045000
b1011110 E
b1011011 5
1&
#1050000
0&
#1055000
b1011100 5
b1011111 E
1&
#1060000
0&
#1065000
b1100000 E
b1011101 5
1&
#1070000
0&
#1075000
b1011110 5
b1100001 E
1&
#1080000
0&
#1085000
b1100010 E
b1011111 5
1&
#1090000
0&
#1095000
b1100000 5
b1100011 E
1&
#1100000
0&
#1105000
b1100100 E
b1100001 5
1&
#1110000
0&
#1115000
b1100010 5
b1100101 E
1&
#1120000
0&
#1125000
b1100110 E
b1100011 5
1&
#1130000
0&
#1135000
b1100100 5
b1100111 E
1&
#1140000
0&
#1145000
b1101000 E
b1100101 5
1&
#1150000
0&
#1155000
b1100110 5
b1101001 E
1&
#1160000
0&
#1165000
b1101010 E
b1100111 5
1&
#1170000
0&
#1175000
b1101000 5
b1101011 E
1&
#1180000
0&
#1185000
b1101100 E
b1101001 5
1&
#1190000
0&
#1195000
b1101010 5
b1101101 E
1&
#1200000
0&
#1205000
b1101110 E
b1101011 5
1&
#1210000
0&
#1215000
b1101100 5
b1101111 E
1&
#1220000
0&
#1225000
b1110000 E
b1101101 5
1&
#1230000
0&
#1235000
b1101110 5
b1110001 E
1&
#1240000
0&
#1245000
b1110010 E
b1101111 5
1&
#1250000
0&
#1255000
b1110000 5
b1110011 E
1&
#1260000
0&
#1265000
b1110100 E
b1110001 5
1&
#1270000
0&
#1275000
b1110010 5
b1110101 E
1&
#1280000
0&
#1285000
b1110110 E
b1110011 5
1&
#1290000
0&
#1295000
b1110100 5
b1110111 E
1&
#1300000
0&
#1305000
b1111000 E
b1110101 5
1&
#1310000
0&
#1315000
b1110110 5
b1111001 E
1&
#1320000
0&
#1325000
b1111010 E
b1110111 5
1&
#1330000
0&
#1335000
b1111000 5
b1111011 E
1&
#1340000
0&
#1345000
b1111100 E
b1111001 5
1&
#1350000
0&
#1355000
b1111010 5
b1111101 E
1&
#1360000
0&
#1365000
b1111110 E
b1111011 5
1&
#1370000
0&
#1375000
b1111100 5
b1111111 E
1&
#1380000
0&
#1385000
b10000000 E
b1111101 5
1&
#1390000
0&
#1395000
b1111110 5
b10000001 E
1&
#1400000
0&
#1405000
b10000010 E
b1111111 5
1&
#1410000
0&
#1415000
b10000000 5
b10000011 E
1&
#1420000
0&
#1425000
b10000100 E
b10000001 5
1&
#1430000
0&
#1435000
b10000010 5
b10000101 E
1&
#1440000
0&
#1445000
b10000110 E
b10000011 5
1&
#1450000
0&
#1455000
b10000100 5
b10000111 E
1&
#1460000
0&
#1465000
b10001000 E
b10000101 5
1&
#1470000
0&
#1475000
b10000110 5
b10001001 E
1&
#1480000
0&
#1485000
b10001010 E
b10000111 5
1&
#1490000
0&
#1495000
b10001000 5
b10001011 E
1&
#1500000
0&
#1505000
b10001100 E
b10001001 5
1&
#1510000
0&
#1515000
b10001010 5
b10001101 E
1&
#1520000
0&
#1525000
b10001110 E
b10001011 5
1&
#1530000
0&
#1535000
b10001100 5
b10001111 E
1&
#1540000
0&
#1545000
b10010000 E
b10001101 5
1&
#1550000
0&
#1555000
b10001110 5
b10010001 E
1&
#1560000
0&
#1565000
b10010010 E
b10001111 5
1&
#1570000
0&
#1575000
b10010000 5
b10010011 E
1&
#1580000
0&
#1585000
b10010100 E
b10010001 5
1&
#1590000
0&
#1595000
b10010010 5
b10010101 E
1&
#1600000
0&
#1605000
b10010110 E
b10010011 5
1&
#1610000
0&
#1615000
b10010100 5
b10010111 E
1&
#1620000
0&
#1625000
b10011000 E
b10010101 5
1&
#1630000
0&
#1635000
b10010110 5
b10011001 E
1&
#1640000
0&
#1645000
b10011010 E
b10010111 5
1&
#1650000
0&
#1655000
b10011000 5
b10011011 E
1&
#1660000
0&
#1665000
b10011100 E
b10011001 5
1&
#1670000
0&
#1675000
b10011010 5
b10011101 E
1&
#1680000
0&
#1685000
b10011110 E
b10011011 5
1&
#1690000
0&
#1695000
b10011100 5
b10011111 E
1&
#1700000
0&
#1705000
b10100000 E
b10011101 5
1&
#1710000
0&
#1715000
b10011110 5
b10100001 E
1&
#1720000
0&
#1725000
b10100010 E
b10011111 5
1&
#1730000
0&
#1735000
b10100000 5
b10100011 E
1&
#1740000
0&
#1745000
b10100100 E
b10100001 5
1&
#1750000
0&
#1755000
b10100010 5
b10100101 E
1&
#1760000
0&
#1765000
b10100110 E
b10100011 5
1&
#1770000
0&
#1775000
b10100100 5
b10100111 E
1&
#1780000
0&
#1785000
b10101000 E
b10100101 5
1&
#1790000
0&
#1795000
b10100110 5
b10101001 E
1&
#1800000
0&
#1805000
b10101010 E
b10100111 5
1&
#1810000
0&
#1815000
b10101000 5
b10101011 E
1&
#1820000
0&
#1825000
b10101100 E
b10101001 5
1&
#1830000
0&
#1835000
b10101010 5
b10101101 E
1&
#1840000
0&
#1845000
b10101110 E
b10101011 5
1&
#1850000
0&
#1855000
b10101100 5
b10101111 E
1&
#1860000
0&
#1865000
b10110000 E
b10101101 5
1&
#1870000
0&
#1875000
b10101110 5
b10110001 E
1&
#1880000
0&
#1885000
b10110010 E
b10101111 5
1&
#1890000
0&
#1895000
b10110000 5
b10110011 E
1&
#1900000
0&
#1905000
b10110100 E
b10110001 5
1&
#1910000
0&
#1915000
b10110010 5
b10110101 E
1&
#1920000
0&
#1925000
b10110110 E
b10110011 5
1&
#1930000
0&
#1935000
b10110100 5
b10110111 E
1&
#1940000
0&
#1945000
b10111000 E
b10110101 5
1&
#1950000
0&
#1955000
b10110110 5
b10111001 E
1&
#1960000
0&
#1965000
b10111010 E
b10110111 5
1&
#1970000
0&
#1975000
b10111000 5
b10111011 E
1&
#1980000
0&
#1985000
b10111100 E
b10111001 5
1&
#1990000
0&
#1995000
b10111010 5
b10111101 E
1&
#2000000
0&
#2005000
b10111110 E
b10111011 5
1&
#2010000
0&
#2015000
b10111100 5
b10111111 E
1&
#2020000
0&
#2025000
b11000000 E
b10111101 5
1&
#2030000
0&
#2035000
b10111110 5
b11000001 E
1&
#2040000
0&
#2045000
b11000010 E
b10111111 5
1&
#2050000
0&
#2055000
b11000000 5
b11000011 E
1&
#2060000
0&
#2065000
b11000100 E
b11000001 5
1&
#2070000
0&
#2075000
b11000010 5
b11000101 E
1&
#2080000
0&
#2085000
b11000110 E
b11000011 5
1&
#2090000
0&
#2095000
b11000100 5
b11000111 E
1&
#2100000
0&
#2105000
b11001000 E
b11000101 5
1&
#2110000
0&
#2115000
b11000110 5
b11001001 E
1&
#2120000
0&
#2125000
b11001010 E
b11000111 5
1&
#2130000
0&
#2135000
b11001000 5
b11001011 E
1&
#2140000
0&
#2145000
b11001100 E
b11001001 5
1&
#2150000
0&
#2155000
b11001010 5
b11001101 E
1&
#2160000
0&
#2165000
b11001110 E
b11001011 5
1&
#2170000
0&
#2175000
b11001100 5
b11001111 E
1&
#2180000
0&
#2185000
b11010000 E
b11001101 5
1&
#2190000
0&
#2195000
b11001110 5
b11010001 E
1&
#2200000
0&
#2205000
b11010010 E
b11001111 5
1&
#2210000
0&
#2215000
b11010000 5
b11010011 E
1&
#2220000
0&
#2225000
b11010100 E
b11010001 5
1&
#2230000
0&
#2235000
b11010010 5
b11010101 E
1&
#2240000
0&
#2245000
b11010110 E
b11010011 5
1&
#2250000
0&
#2255000
b11010100 5
b11010111 E
1&
#2260000
0&
#2265000
b11011000 E
b11010101 5
1&
#2270000
0&
#2275000
b11010110 5
b11011001 E
1&
#2280000
0&
#2285000
b11011010 E
b11010111 5
1&
#2290000
0&
#2295000
b11011000 5
b11011011 E
1&
#2300000
0&
#2305000
b11011100 E
b11011001 5
1&
#2310000
0&
#2315000
b11011010 5
b11011101 E
1&
#2320000
0&
#2325000
b11011110 E
b11011011 5
1&
#2330000
0&
#2335000
b11011100 5
b11011111 E
1&
#2340000
0&
#2345000
b11100000 E
b11011101 5
1&
#2350000
0&
#2355000
b11011110 5
b11100001 E
1&
#2360000
0&
#2365000
b11100010 E
b11011111 5
1&
#2370000
0&
#2375000
b11100000 5
b11100011 E
1&
#2380000
0&
#2385000
b11100100 E
b11100001 5
1&
#2390000
0&
#2395000
b11100010 5
b11100101 E
1&
#2400000
0&
#2405000
b11100110 E
b11100011 5
1&
#2410000
0&
#2415000
b11100100 5
b11100111 E
1&
#2420000
0&
#2425000
b11101000 E
b11100101 5
1&
#2430000
0&
#2435000
b11100110 5
b11101001 E
1&
#2440000
0&
#2445000
b11101010 E
b11100111 5
1&
#2450000
0&
#2455000
b11101000 5
b11101011 E
1&
#2460000
0&
#2465000
b11101100 E
b11101001 5
1&
#2470000
0&
#2475000
b11101010 5
b11101101 E
1&
#2480000
0&
#2485000
b11101110 E
b11101011 5
1&
#2490000
0&
#2495000
b11101100 5
b11101111 E
1&
#2500000
0&
#2505000
b11110000 E
b11101101 5
1&
#2510000
0&
#2515000
b11101110 5
b11110001 E
1&
#2520000
0&
#2525000
b11110010 E
b11101111 5
1&
#2530000
0&
#2535000
b11110000 5
b11110011 E
1&
#2540000
0&
#2545000
b11110100 E
b11110001 5
1&
#2550000
0&
#2555000
b11110010 5
b11110101 E
1&
#2560000
0&
#2565000
b11110110 E
b11110011 5
1&
#2570000
0&
#2575000
b11110100 5
b11110111 E
1&
#2580000
0&
#2585000
b11111000 E
b11110101 5
1&
#2590000
0&
#2595000
b11110110 5
b11111001 E
1&
#2600000
0&
#2605000
b11111010 E
b11110111 5
1&
#2610000
0&
#2615000
b11111000 5
b11111011 E
1&
#2620000
0&
#2625000
b11111100 E
b11111001 5
1&
#2630000
0&
#2635000
b11111010 5
b11111101 E
1&
#2640000
0&
#2645000
b11111110 E
b11111011 5
1&
#2650000
0&
#2655000
b11111100 5
b11111111 E
1&
#2660000
0&
#2665000
b100000000 E
b11111101 5
1&
#2670000
0&
#2675000
b11111110 5
b100000001 E
1&
#2680000
0&
#2685000
b100000010 E
b11111111 5
1&
#2690000
0&
#2695000
b100000000 5
b100000011 E
1&
#2700000
0&
#2705000
b100000100 E
b100000001 5
1&
#2710000
0&
#2715000
b100000010 5
b100000101 E
1&
#2720000
0&
#2725000
b100000110 E
b100000011 5
1&
#2730000
0&
#2735000
b100000100 5
b100000111 E
1&
#2740000
0&
#2745000
b100001000 E
b100000101 5
1&
#2750000
0&
#2755000
b100000110 5
b100001001 E
1&
#2760000
0&
#2765000
b100001010 E
b100000111 5
1&
#2770000
0&
#2775000
b100001000 5
b100001011 E
1&
#2780000
0&
#2785000
b100001100 E
b100001001 5
1&
#2790000
0&
#2795000
b100001010 5
b100001101 E
1&
#2800000
0&
#2805000
b100001110 E
b100001011 5
1&
#2810000
0&
#2815000
b100001100 5
b100001111 E
1&
#2820000
0&
#2825000
b100010000 E
b100001101 5
1&
#2830000
0&
#2835000
b100001110 5
b100010001 E
1&
#2840000
0&
#2845000
b100010010 E
b100001111 5
1&
#2850000
0&
#2855000
b100010000 5
b100010011 E
1&
#2860000
0&
#2865000
b100010100 E
b100010001 5
1&
#2870000
0&
#2875000
b100010010 5
b100010101 E
1&
#2880000
0&
#2885000
b100010110 E
b100010011 5
1&
#2890000
0&
#2895000
b100010100 5
b100010111 E
1&
#2900000
0&
#2905000
b100011000 E
b100010101 5
1&
#2910000
0&
#2915000
b100010110 5
b100011001 E
1&
#2920000
0&
#2925000
b100011010 E
b100010111 5
1&
#2930000
0&
#2935000
b100011000 5
b100011011 E
1&
#2940000
0&
